QApedia/__init__.py
QApedia/generator.py
QApedia/io.py
QApedia/qapedia.py
QApedia/utils.py
QApedia/data/example.csv
QApedia/data/prefixes.txt
tests/__init__.py
tests/conftest.py
tests/test_generator.py
tests/test_io.py
tests/test_qapedia.py
tests/test_utils.py
QA_pedia-0.0.0a0.dist-info/LICENSE
QA_pedia-0.0.0a0.dist-info/METADATA
QA_pedia-0.0.0a0.dist-info/WHEEL
QA_pedia-0.0.0a0.dist-info/entry_points.txt
QA_pedia-0.0.0a0.dist-info/top_level.txt
QA_pedia-0.0.0a0.dist-info/RECORD
