Metadata-Version: 2.1
Name: QA-pedia
Version: 0.0.0a0
Summary: Geração de pares questão-sparql
Home-page: https://github.com/QApedia/QApedia
Author: Ivan Pereira, Jessica Sousa
Author-email: navi1921@gmail.com, jessicasousa.pc@gmail.com
License: MIT
Platform: UNKNOWN
Classifier: Environment :: Console
Classifier: Operating System :: OS Independent
Classifier: Intended Audience :: Developers
Classifier: Intended Audience :: Other Audience
Classifier: Topic :: Software Development :: Libraries :: Python Modules
Classifier: License :: OSI Approved :: MIT License
Classifier: Programming Language :: Python :: 3.6
Classifier: Programming Language :: Python :: 3.7
Classifier: Programming Language :: Python :: Implementation :: PyPy
Requires-Python: >=3.6
Requires-Dist: SPARQLWrapper
Requires-Dist: pandas
Requires-Dist: lxml
